[
    {
        "id": "LUM-178401790046",
        "nombre": "Aura Difusor Essential",
        "precio": 200,
        "categoria": "Hogar",
        "descripcion": "Selecci\u00f3n de alta gama curada por Lumina Select para elevar su estilo de vida.",
        "imagen": "https://images.unsplash.com/photo-1583847268964-b28dc2f51ac9?w=800"
    },
    {
        "id": "LUM-178402461655",
        "nombre": "Lumina Auriculares Pro 7",
        "precio": 95,
        "categoria": "Tecnolog\u00eda",
        "descripcion": "Selecci\u00f3n de alta gama curada por Lumina Select para elevar su estilo de vida.",
        "imagen": "https://images.unsplash.com/photo-1491933382434-500287f9b54b?w=800"
    },
    {
        "id": "LUM-178403047063",
        "nombre": "Zen Sensor de Cultivo",
        "precio": 165,
        "categoria": "Jardiner\u00eda",
        "descripcion": "Selecci\u00f3n de alta gama curada por Lumina Select para elevar su estilo de vida.",
        "imagen": "https://images.unsplash.com/photo-1485955900006-10f4d324d411?w=800"
    },
    {
        "id": "LUM-178403870634",
        "nombre": "Zen Kit Bot\u00e1nico 6",
        "precio": 277,
        "categoria": "Jardiner\u00eda",
        "descripcion": "Selecci\u00f3n de alta gama curada por Lumina Select para elevar su estilo de vida.",
        "imagen": "https://images.unsplash.com/photo-1485955900006-10f4d324d411?w=800"
    },
    {
        "id": "LUM-178404439047",
        "nombre": "Elite Maceta WiFi",
        "precio": 186,
        "categoria": "Jardiner\u00eda",
        "descripcion": "Selecci\u00f3n de alta gama curada por Lumina Select para elevar su estilo de vida.",
        "imagen": "https://images.unsplash.com/photo-1617576621334-4291ef387ae4?w=800"
    },
    {
        "id": "LUM-178404967689",
        "nombre": "Neo Auriculares Pro",
        "precio": 130,
        "categoria": "Tecnolog\u00eda",
        "descripcion": "Selecci\u00f3n de alta gama curada por Lumina Select para elevar su estilo de vida.",
        "imagen": "https://images.unsplash.com/photo-1491933382434-500287f9b54b?w=800"
    },
    {
        "id": "LUM-178405476899",
        "nombre": "Elite Kit Bot\u00e1nico",
        "precio": 360,
        "categoria": "Jardiner\u00eda",
        "descripcion": "Selecci\u00f3n de alta gama curada por Lumina Select para elevar su estilo de vida.",
        "imagen": "https://images.unsplash.com/photo-1485955900006-10f4d324d411?w=800"
    },
    {
        "id": "LUM-178406027381",
        "nombre": "Neo Kit Bot\u00e1nico",
        "precio": 278,
        "categoria": "Jardiner\u00eda",
        "descripcion": "Selecci\u00f3n de alta gama curada por Lumina Select para elevar su estilo de vida.",
        "imagen": "https://images.unsplash.com/photo-1485955900006-10f4d324d411?w=800"
    },
    {
        "id": "LUM-178406442911",
        "nombre": "Elite L\u00e1mpara Orbital",
        "precio": 124,
        "categoria": "Hogar",
        "descripcion": "Selecci\u00f3n de alta gama curada por Lumina Select para elevar su estilo de vida.",
        "imagen": "https://images.unsplash.com/photo-1544190153-060cb6277f67?w=800"
    },
    {
        "id": "LUM-178406870756",
        "nombre": "Neo Proyector 4K",
        "precio": 344,
        "categoria": "Tecnolog\u00eda",
        "descripcion": "Selecci\u00f3n de alta gama curada por Lumina Select para elevar su estilo de vida.",
        "imagen": "https://images.unsplash.com/photo-1511467687858-23d96c32e4ae?w=800"
    },
    {
        "id": "LUM-178407208724",
        "nombre": "Elite Difusor Essential",
        "precio": 226,
        "categoria": "Hogar",
        "descripcion": "Selecci\u00f3n de alta gama curada por Lumina Select para elevar su estilo de vida.",
        "imagen": "https://images.unsplash.com/photo-1567538096630-e0c55bd6374c?w=800"
    },
    {
        "id": "LUM-178407716344",
        "nombre": "Aura C\u00e1mara Hub",
        "precio": 58,
        "categoria": "Tecnolog\u00eda",
        "descripcion": "Selecci\u00f3n de alta gama curada por Lumina Select para elevar su estilo de vida.",
        "imagen": "https://images.unsplash.com/photo-1491933382434-500287f9b54b?w=800"
    }
]